{
    "name": "your-name/your-api",
    "description": "Your API description",
    "type": "project",
    "license": "MIT",
    "require": {
        "php": "^8.0",
        "laravel/framework": "^9.0"
    },
    "require-dev": {
        "fzaninotto/faker": "^1.9.1",
        "mockery/mockery": "^1.4.4",
        "phpunit/phpunit": "^9.5.5"
    },
    "autoload": {
        "psr-4": {
            "App\\": "app/"
        }
    },
    "autoload-dev": {
        "psr-4": {
            "Tests\\": "tests/"
        }
    },
    "scripts": {
        "test": [
            "phpunit"
        ]
    }
}

